PySide6/PySide6_Addons.json
PySide6/Qt3DAnimation.pyd
PySide6/Qt3DAnimation.pyi
PySide6/Qt3DCore.pyd
PySide6/Qt3DCore.pyi
PySide6/Qt3DExtras.pyd
PySide6/Qt3DExtras.pyi
PySide6/Qt3DInput.pyd
PySide6/Qt3DInput.pyi
PySide6/Qt3DLogic.pyd
PySide6/Qt3DLogic.pyi
PySide6/Qt3DRender.pyd
PySide6/Qt3DRender.pyi
PySide6/Qt63DAnimation.dll
PySide6/Qt63DCore.dll
PySide6/Qt63DExtras.dll
PySide6/Qt63DInput.dll
PySide6/Qt63DLogic.dll
PySide6/Qt63DQuick.dll
PySide6/Qt63DQuickAnimation.dll
PySide6/Qt63DQuickExtras.dll
PySide6/Qt63DQuickInput.dll
PySide6/Qt63DQuickLogic.dll
PySide6/Qt63DQuickRender.dll
PySide6/Qt63DQuickScene2D.dll
PySide6/Qt63DQuickScene3D.dll
PySide6/Qt63DRender.dll
PySide6/Qt6Bluetooth.dll
PySide6/Qt6Charts.dll
PySide6/Qt6ChartsQml.dll
PySide6/Qt6DataVisualization.dll
PySide6/Qt6DataVisualizationQml.dll
PySide6/Qt6Graphs.dll
PySide6/Qt6GraphsWidgets.dll
PySide6/Qt6HttpServer.dll
PySide6/Qt6Location.dll
PySide6/Qt6Multimedia.dll
PySide6/Qt6MultimediaQuick.dll
PySide6/Qt6MultimediaWidgets.dll
PySide6/Qt6NetworkAuth.dll
PySide6/Qt6Nfc.dll
PySide6/Qt6Pdf.dll
PySide6/Qt6PdfQuick.dll
PySide6/Qt6PdfWidgets.dll
PySide6/Qt6Positioning.dll
PySide6/Qt6PositioningQuick.dll
PySide6/Qt6Quick3D.dll
PySide6/Qt6Quick3DAssetImport.dll
PySide6/Qt6Quick3DAssetUtils.dll
PySide6/Qt6Quick3DEffects.dll
PySide6/Qt6Quick3DGlslParser.dll
PySide6/Qt6Quick3DHelpers.dll
PySide6/Qt6Quick3DHelpersImpl.dll
PySide6/Qt6Quick3DIblBaker.dll
PySide6/Qt6Quick3DParticleEffects.dll
PySide6/Qt6Quick3DParticles.dll
PySide6/Qt6Quick3DRuntimeRender.dll
PySide6/Qt6Quick3DSpatialAudio.dll
PySide6/Qt6Quick3DUtils.dll
PySide6/Qt6Quick3DXr.dll
PySide6/Qt6RemoteObjects.dll
PySide6/Qt6RemoteObjectsQml.dll
PySide6/Qt6Scxml.dll
PySide6/Qt6ScxmlQml.dll
PySide6/Qt6Sensors.dll
PySide6/Qt6SensorsQuick.dll
PySide6/Qt6SerialBus.dll
PySide6/Qt6SerialPort.dll
PySide6/Qt6ShaderTools.dll
PySide6/Qt6SpatialAudio.dll
PySide6/Qt6StateMachine.dll
PySide6/Qt6StateMachineQml.dll
PySide6/Qt6TextToSpeech.dll
pyside6_addons-6.9.3.dist-info/licenses/LicenseRef-Qt-Commercial.txt
pyside6_addons-6.9.3.dist-info/METADATA
pyside6_addons-6.9.3.dist-info/WHEEL
pyside6_addons-6.9.3.dist-info/top_level.txt
pyside6_addons-6.9.3.dist-info/RECORD
