Metadata-Version: 2.4
Name: PySide6_Addons
Version: 6.9.3
Summary: Python bindings for the Qt cross-platform application and UI framework (Addons)
Author-email: Qt for Python Team <pyside@qt-project.org>
License: LGPL-3.0-only OR GPL-2.0-only OR GPL-3.0-only
Project-URL: Homepage, https://pyside.org
Project-URL: Documentation, https://doc.qt.io/qtforpython
Project-URL: Repository, https://code.qt.io/cgit/pyside/pyside-setup.git/
Project-URL: Changelog, https://code.qt.io/cgit/pyside/pyside-setup.git/tree/doc/changelogs
Project-URL: Tracker, https://bugreports.qt.io/projects/PYSIDE
Keywords: Qt
Classifier: Development Status :: 5 - Production/Stable
Classifier: Environment :: Console
Classifier: Environment :: MacOS X
Classifier: Environment :: X11 Applications :: Qt
Classifier: Environment :: Win32 (MS Windows)
Classifier: Intended Audience :: Developers
Classifier: Operating System :: MacOS :: MacOS X
Classifier: Operating System :: POSIX
Classifier: Operating System :: POSIX :: Linux
Classifier: Operating System :: Microsoft
Classifier: Operating System :: Microsoft :: Windows
Classifier: Programming Language :: C++
Classifier: Programming Language :: Python
Classifier: Programming Language :: Python :: 3
Classifier: Programming Language :: Python :: 3.9
Classifier: Programming Language :: Python :: 3.10
Classifier: Programming Language :: Python :: 3.11
Classifier: Programming Language :: Python :: 3.12
Classifier: Programming Language :: Python :: 3.13
Classifier: Topic :: Database
Classifier: Topic :: Software Development
Classifier: Topic :: Software Development :: Code Generators
Classifier: Topic :: Software Development :: Libraries :: Application Frameworks
Classifier: Topic :: Software Development :: User Interfaces
Classifier: Topic :: Software Development :: Widget Sets
Requires-Python: <3.14,>=3.9
License-File: LicenseRef-Qt-Commercial.txt
Requires-Dist: shiboken6==6.9.3
Requires-Dist: PySide6_Essentials==6.9.3
Dynamic: license-file
